pytest_metrics/__init__.py
pytest_metrics/decorators.py
pytest_metrics/metrics.py
qase_victoria_metrics-1.2.0.dist-info/METADATA
qase_victoria_metrics-1.2.0.dist-info/WHEEL
qase_victoria_metrics-1.2.0.dist-info/entry_points.txt
qase_victoria_metrics-1.2.0.dist-info/top_level.txt
qase_victoria_metrics-1.2.0.dist-info/RECORD
