Metadata-Version: 2.4
Name: qase-victoria-metrics
Version: 1.2.0
Summary: A Qase-Pytest plugin to extract test results and push metrics to Victoria Metrics
Home-page: https://github.com/dsetiawan230294/qase-victoria-metrics
Author: Didit Setiawan
Author-email: Didit Setiawan <didit@pintu.co.id>
License: MIT
Keywords: pytest,qase,metrics,victoria-metrics,pytest-plugin
Classifier: Framework :: Pytest
Classifier: Programming Language :: Python :: 3.10
Classifier: License :: OSI Approved :: MIT License
Classifier: Operating System :: OS Independent
Requires-Python: >=3.10
Requires-Dist: pytest>=8.3.5
Requires-Dist: qase-pytest>=6.2.0
Requires-Dist: allure-pytest>=2.13.5
Dynamic: author
Dynamic: home-page
Dynamic: requires-python
